.gitignore
COPYING
LICENSE
MANIFEST.in
Makefile
PKG-INFO
README.md
setup.py
uninstall.sh
update-git.sh
app_data/mosaicode.desktop
app_data/images/StereoLeft.jpg
app_data/images/StereoRight.jpg
app_data/images/aviao.png
app_data/images/baboon.png
app_data/images/elaine.png
app_data/images/finep_logo.gif
app_data/images/foto_satelite.png
app_data/images/garota_01.png
app_data/images/haarcascade_frontalface_alt2.xml
app_data/images/lenna.png
app_data/images/mosaicode-old.ico
app_data/images/mosaicode-old.png
app_data/images/mosaicode.bmp
app_data/images/mosaicode.ico
app_data/images/mosaicode.png
app_data/images/mosaicode.svg
app_data/images/mosaicode.xpm
app_data/images/mosaicode2.png
app_data/images/mosaicode64x64.ico
app_data/images/mosaicode_2.bmp
app_data/images/mosaicode_ave.png
app_data/images/mosaicode_ave_small.png
app_data/images/mosaicode_foto.jpg
app_data/images/mosaicode_name.png
app_data/images/mosaicode_small_inst.bmp
app_data/images/relogio.png
app_data/images/s2ilogo.png
app_data/images/s2ilogo48.png
app_data/images/sementes.png
app_data/images/tanque.png
app_data/images/vLeft.mpg
app_data/images/vRight.mpg
debian/changelog
debian/compat
debian/control
debian/rules
docs/Makefile
docs/make.bat
docs/source/conf.py
docs/source/index.rst
docs/source/modules.rst
docs/source/mosaicode.GUI.components.rst
docs/source/mosaicode.GUI.rst
docs/source/mosaicode.control.rst
docs/source/mosaicode.model.rst
docs/source/mosaicode.plugins.C.openCV.rst
docs/source/mosaicode.plugins.C.rst
docs/source/mosaicode.plugins.javascript.rst
docs/source/mosaicode.plugins.javascript.webaudio.rst
docs/source/mosaicode.plugins.rst
docs/source/mosaicode.rst
docs/source/mosaicode.utils.rst
docs/source/setup.rst
docs/source/test.control.rst
docs/source/test.rst
docs/source/_themes/sphinx_rtd_theme/__init__.py
docs/source/_themes/sphinx_rtd_theme/breadcrumbs.html
docs/source/_themes/sphinx_rtd_theme/footer.html
docs/source/_themes/sphinx_rtd_theme/layout.html
mosaicode.egg-info/PKG-INFO
mosaicode.egg-info/SOURCES.txt
mosaicode.egg-info/dependency_links.txt
mosaicode.egg-info/not-zip-safe
mosaicode.egg-info/requires.txt
mosaicode.egg-info/top_level.txt
